airflow_google_cloud_run_plugin/.DS_Store
airflow_google_cloud_run_plugin/__init__.py
airflow_google_cloud_run_plugin/cloud_run_v1/__init__.py
airflow_google_cloud_run_plugin/cloud_run_v1/client.py
airflow_google_cloud_run_plugin/cloud_run_v1/namespaces/__init__.py
airflow_google_cloud_run_plugin/cloud_run_v1/namespaces/execution.py
airflow_google_cloud_run_plugin/cloud_run_v1/namespaces/job.py
airflow_google_cloud_run_plugin/cloud_run_v1/types/__init__.py
airflow_google_cloud_run_plugin/cloud_run_v1/types/condition.py
airflow_google_cloud_run_plugin/cloud_run_v1/types/container.py
airflow_google_cloud_run_plugin/cloud_run_v1/types/execution_spec.py
airflow_google_cloud_run_plugin/cloud_run_v1/types/object_meta.py
airflow_google_cloud_run_plugin/cloud_run_v1/types/task_spec.py
airflow_google_cloud_run_plugin/cloud_run_v1/utils/__init__.py
airflow_google_cloud_run_plugin/cloud_run_v1/utils/mixins.py
airflow_google_cloud_run_plugin/exceptions.py
airflow_google_cloud_run_plugin/hooks/cloud_run.py
airflow_google_cloud_run_plugin/operators/cloud_run/__init__.py
airflow_google_cloud_run_plugin/operators/cloud_run/base.py
airflow_google_cloud_run_plugin/operators/cloud_run/core.py
airflow_google_cloud_run_plugin/operators/cloud_run/crud.py
airflow_google_cloud_run_plugin-0.3.2.dist-info/LICENSE
airflow_google_cloud_run_plugin-0.3.2.dist-info/WHEEL
airflow_google_cloud_run_plugin-0.3.2.dist-info/METADATA
airflow_google_cloud_run_plugin-0.3.2.dist-info/RECORD
