Metadata-Version: 2.1
Name: airflow-google-cloud-run-plugin
Version: 0.3.2
Summary: Airflow plugin for Google Cloud Run Jobs
Home-page: https://github.com/mharrisb1/airflow-google-cloud-run-plugin
License: MIT
Author: Michael Harris
Author-email: mharris@luabase.com
Requires-Python: >=3.8,<3.11
Classifier: License :: OSI Approved :: MIT License
Classifier: Programming Language :: Python :: 3
Classifier: Programming Language :: Python :: 3.8
Classifier: Programming Language :: Python :: 3.9
Classifier: Programming Language :: Python :: 3.10
Requires-Dist: google-auth (>=2.13.0,<3.0.0)
Project-URL: Documentation, https://github.com/mharrisb1/airflow-google-cloud-run-plugin
Project-URL: Repository, https://github.com/mharrisb1/airflow-google-cloud-run-plugin
